MANIFEST.in
README.txt
setup.py
bin/wscrap3
bin/wscrap3.3
pyscrap3/__init__.py
pyscrap3/spiders.py
pyscrap3/utils.py
pyscrap3.egg-info/PKG-INFO
pyscrap3.egg-info/SOURCES.txt
pyscrap3.egg-info/dependency_links.txt
pyscrap3.egg-info/not-zip-safe
pyscrap3.egg-info/requires.txt
pyscrap3.egg-info/top_level.txt
pyscrap3/__pycache__/__init__.cpython-33.pyc
pyscrap3/__pycache__/spiders.cpython-33.pyc
pyscrap3/__pycache__/utils.cpython-33.pyc
pyscrap3/template/.mrbob.ini
pyscrap3/template/+package.name+/.gitignore
pyscrap3/template/+package.name+/HISTORY.rst
pyscrap3/template/+package.name+/LICENSE.bob
pyscrap3/template/+package.name+/MANIFEST.in.bob
pyscrap3/template/+package.name+/NOTICE.bob
pyscrap3/template/+package.name+/README.md.bob
pyscrap3/template/+package.name+/README.rst.bob
pyscrap3/template/+package.name+/setup.py.bob
pyscrap3/template/+package.name+/+package.name+/__init__.py
pyscrap3/template/+package.name+/+package.name+/demoSpider.py
pyscrap3/template/+package.name+/+package.name+/items.py
pyscrap3/template/+package.name+/+package.name+/pipeline.py
pyscrap3/templateUtils/__init__.py
pyscrap3/templateUtils/hooks.py
pyscrap3/templateUtils/__pycache__/__init__.cpython-33.pyc
pyscrap3/templateUtils/__pycache__/hooks.cpython-33.pyc