Metadata-Version: 1.1
Name: pyscrap3
Version: 0.0.13
Summary: micro framework for web scraping
Home-page: https://github.com/Zincr0/pyscrap3
Author: Daniel Mondaca
Author-email: daniel@analitic.cl
License: Apache 2.0 License
Keywords: web scraping
Platform: UNKNOWN
Classifier: Development Status :: 4 - Beta
Classifier: Topic :: Software Development
Classifier: License :: OSI Approved :: Apache Software License
Classifier: Operating System :: POSIX :: Linux
Classifier: Programming Language :: Python :: 3
